easy_tk/EasyTk.py
easy_tk/EasyTkObject.py
easy_tk/TkChild.py
easy_tk/TkMaster.py
easy_tk/__init__.py
easy_tk/helpers.py
easy_tk-1.0.7.3.dist-info/LICENSE
easy_tk-1.0.7.3.dist-info/METADATA
easy_tk-1.0.7.3.dist-info/WHEEL
easy_tk-1.0.7.3.dist-info/top_level.txt
easy_tk-1.0.7.3.dist-info/RECORD
