Metadata-Version: 2.1
Name: easy-tk
Version: 1.0.7.3
Summary: Make Tkinter apps in an easy way using JSON.
Home-page: https://github.com/uros-5/easy-tk
Author: Uros Mrkobrada
Author-email: 
License: GNU General Public License v3
Platform: any
Classifier: Development Status :: 5 - Production/Stable
Classifier: Topic :: Software Development :: User Interfaces
Classifier: Topic :: Utilities
Classifier: Topic :: Desktop Environment
Classifier: Intended Audience :: Developers
Classifier: License :: OSI Approved :: GNU General Public License v3 (GPLv3)
Classifier: Operating System :: OS Independent
Classifier: Programming Language :: Python
Requires-Dist: tkintertable
Provides-Extra: dev
Requires-Dist: pytest (>=3.6) ; extra == 'dev'
